sqlalchemy_nav/__init__.py
sqlalchemy_nav/base.py
sqlalchemy_nav/brand.py
sqlalchemy_nav/dropdownitem.html
sqlalchemy_nav/dropdownitem.py
sqlalchemy_nav/navbar.html
sqlalchemy_nav/navbar.py
sqlalchemy_nav/navitem.html
sqlalchemy_nav/navitem.py
sqlalchemy_nav/navitemdropdown.html
sqlalchemy_nav-0.0.5.dist-info/LICENSE
sqlalchemy_nav-0.0.5.dist-info/METADATA
sqlalchemy_nav-0.0.5.dist-info/WHEEL
sqlalchemy_nav-0.0.5.dist-info/top_level.txt
sqlalchemy_nav-0.0.5.dist-info/RECORD
