Metadata-Version: 2.1
Name: sqlalchemy-nav
Version: 0.0.5
Summary: SQLAlchemy-Nav makes it easy to create and customize dynamic Bootstrap 4 Navbars for web apps with a SQLAlchemy backend.
Home-page: https://dsbowen.github.io/sqlalchemy-nav
Author: Dillon Bowen
Author-email: dsbowen@wharton.upenn.edu
License: UNKNOWN
Platform: UNKNOWN
Classifier: Programming Language :: Python :: 3
Classifier: License :: OSI Approved :: MIT License
Classifier: Operating System :: OS Independent
Requires-Python: >=3.6
Requires-Dist: flask (>=1.1.1)
Requires-Dist: sqlalchemy (>=1.3.12)
Requires-Dist: sqlalchemy-modelid (>=0.0.2)
Requires-Dist: sqlalchemy-mutablesoup (>=0.0.6)
Requires-Dist: sqlalchemy-orderingitem (>=0.0.3)
